nuxl_rescore/Data_parser.py
nuxl_rescore/FDR_calculation.py
nuxl_rescore/NA_Encoding.py
nuxl_rescore/RT_features.py
nuxl_rescore/__init__.py
nuxl_rescore/__main__.py
nuxl_rescore/cli.py
nuxl_rescore/entrapment.py
nuxl_rescore/idXML2df.py
nuxl_rescore/main.py
nuxl_rescore/ms2pip_features.py
nuxl_rescore/plotting.py
nuxl_rescore/run.py
nuxl_rescore-0.4.0.dist-info/licenses/LICENSE
nuxl_rescore-0.4.0.dist-info/METADATA
nuxl_rescore-0.4.0.dist-info/WHEEL
nuxl_rescore-0.4.0.dist-info/entry_points.txt
nuxl_rescore-0.4.0.dist-info/top_level.txt
nuxl_rescore-0.4.0.dist-info/RECORD
