Metadata-Version: 2.4
Name: nuxl_rescore
Version: 0.4.0
Summary: NuXL_rescore: rescoring pipeline for protein‐nucleic acid cross‐links.
Author: Arslan Siraj, Timo Sachsenberg
Author-email: Arslan Siraj <arslan.siraj@uni-tuebingen.de>
License: Apache License
Project-URL: GitHub, https://github.com/Arslan-Siraj/NuXL_rescore/
Project-URL: PyPi, https://pypi.org/project/nuxl_rescore/
Project-URL: OpenMS, https://openms.de/
Keywords: Proteomics,deep learning,cross‐links peptides,retention time,prediction,rescoring
Classifier: Intended Audience :: Science/Research
Classifier: Programming Language :: Python :: 3
Classifier: Operating System :: OS Independent
Classifier: Topic :: Scientific/Engineering :: Bio-Informatics
Requires-Python: >=3.10
License-File: LICENSE
Requires-Dist: numpy>=1.17
Requires-Dist: pandas>=0.25
Requires-Dist: scipy<1.14,>=1.10
Requires-Dist: scikit-learn>=1.2.0
Requires-Dist: tqdm<5,>=4.66
Requires-Dist: statsmodels<0.16,>=0.14
Requires-Dist: matplotlib<3.9,>=3.7
Requires-Dist: pyopenms<=3.2.0,>=2.7
Requires-Dist: deeplcretrainer==0.1.17
Requires-Dist: ms2pip<3.12,>=3.11
Requires-Dist: psm_utils>=0.2.3
Requires-Dist: deeplc==1.2.1
Dynamic: license-file
